invert/__init__.py
invert/config.py
invert/invert.py
invert/adapters/__init__.py
invert/adapters/context_lstm.py
invert/adapters/focuss.py
invert/adapters/stamp.py
invert/cmaps/__init__.py
invert/cmaps/cmaps.py
invert/ensemble/__init__.py
invert/ensemble/ensemble.py
invert/evaluate/__init__.py
invert/evaluate/evaluate.py
invert/forward/__init__.py
invert/forward/forward.py
invert/simulate/__init__.py
invert/simulate/simulate.py
invert/solvers/__init__.py
invert/solvers/base.py
invert/solvers/basis_functions.py
invert/solvers/bayes.py
invert/solvers/beamformer.py
invert/solvers/empirical_bayes.py
invert/solvers/epifocus.py
invert/solvers/esinet.py
invert/solvers/loreta.py
invert/solvers/matching_pursuit.py
invert/solvers/minimum_norm_estimates.py
invert/solvers/msp.py
invert/solvers/music.py
invert/solvers/smap.py
invert/solvers/smooth_matching_pursuit.py
invert/solvers/wrop.py
invert/util/__init__.py
invert/util/util.py
invertmeeg-0.1.0.dist-info/LICENSE
invertmeeg-0.1.0.dist-info/METADATA
invertmeeg-0.1.0.dist-info/WHEEL
invertmeeg-0.1.0.dist-info/top_level.txt
invertmeeg-0.1.0.dist-info/RECORD
