Metadata-Version: 2.1
Name: invertmeeg
Version: 0.1.0
Summary: A high-level M/EEG Python library for EEG inverse solutions
Home-page: https://github.com/LukeTheHecker/inverse
Author: Lukas Hecker
License: CC BY-NC 4.0
Classifier: Programming Language :: Python :: 3
Classifier: License :: Other/Proprietary License
Classifier: Operating System :: OS Independent
Requires-Python: >=3.8
License-File: LICENSE
Requires-Dist: tensorflow
Requires-Dist: mne
Requires-Dist: scipy
Requires-Dist: colorednoise
Requires-Dist: matplotlib
Requires-Dist: pyvista
Requires-Dist: pyvistaqt
Requires-Dist: PyQt5
Requires-Dist: tqdm
Requires-Dist: pytest
Requires-Dist: scikit-learn
Requires-Dist: pandas
Requires-Dist: POT
